etri_klesa_naver_news_crawler/__init__.py
etri_klesa_naver_news_crawler/server.py
etri_klesa_naver_news_crawler-0.1.1.dist-info/METADATA
etri_klesa_naver_news_crawler-0.1.1.dist-info/WHEEL
etri_klesa_naver_news_crawler-0.1.1.dist-info/entry_points.txt
etri_klesa_naver_news_crawler-0.1.1.dist-info/RECORD
